LICENSE.rst
MANIFEST.in
README.rst
setup.py
uml-compliance.rst
src/node/__init__.py
src/node.ext.uml.egg-info/PKG-INFO
src/node.ext.uml.egg-info/SOURCES.txt
src/node.ext.uml.egg-info/dependency_links.txt
src/node.ext.uml.egg-info/entry_points.txt
src/node.ext.uml.egg-info/namespace_packages.txt
src/node.ext.uml.egg-info/requires.txt
src/node.ext.uml.egg-info/top_level.txt
src/node.ext.uml.egg-info/zip-safe
src/node/ext/__init__.py
src/node/ext/uml/__init__.py
src/node/ext/uml/activities.py
src/node/ext/uml/activities.rst
src/node/ext/uml/classes.py
src/node/ext/uml/classes.rst
src/node/ext/uml/core.py
src/node/ext/uml/core.rst
src/node/ext/uml/interfaces.py
src/node/ext/uml/tests.py
src/node/ext/uml/utils.py
src/node/ext/uml/utils.rst
src/node/ext/uml/testing/__init__.py
src/node/ext/uml/testing/env.py